sigma_helper/__init__.py
sigma_helper/sigma_dq_helper_execute_validation_stmnts.py
sigma_helper/sigma_dq_helper_generate_dq_action.py
sigma_helper/sigma_dq_helper_generate_dq_message.py
sigma_helper/sigma_dq_helper_generate_final_result.py
sigma_helper/sigma_dq_helper_generate_run_id.py
sigma_helper/sigma_dq_helper_generate_update_condition.py
sigma_helper/sigma_dq_helper_generate_validation_suite.py
sigma_helper/sigma_dq_helper_unique_elements_in_list.py
sigma_helper/sigma_dq_helper_update_dqaction_dqmessage.py
sigma_helper-0.0.2.dist-info/METADATA
sigma_helper-0.0.2.dist-info/WHEEL
sigma_helper-0.0.2.dist-info/RECORD
