Metadata-Version: 2.1
Name: sigma_helper
Version: 0.0.2
Summary: data quality helper functions
Author-email: sigmoid <ajitg@sigmoidanalytics.com>
Classifier: Programming Language :: Python :: 3
Requires-Python: >=3.7
